{"timestamp":1771781638.5425885,"data":[{"data":"2026.02.07 sobota","od":"9:00","do":"10:30","godziny":"2h00m","group_code":"","przedmiot":"Egzamin: Historia nowych mediów","typ":"","sala":"","prowadzacy":"dr Barbara Cyrek","zaliczenie":"","uwagi":"Egzamin online"},{"data":"2026.02.28 sobota","od":"8:00","do":"8:45","godziny":"1h00m","group_code":"","przedmiot":"Metodologia badań komunikacji społecznej i mediów","typ":"Wyk","sala":"S55 27-AULA","prowadzacy":"dr Magdalena Parus-Jankowska","zaliczenie":"Zaliczenie ocena","uwagi":"Brak"},{"data":"2026.02.28 sobota","od":"9:00","do":"10:30","godziny":"2h00m","group_code":"","przedmiot":"Metodologia badań komunikacji społecznej i mediów","typ":"Wyk","sala":"S55 27-AULA","prowadzacy":"dr Magdalena Parus-Jankowska","zaliczenie":"Zaliczenie ocena","uwagi":"Brak"},{"data":"2026.02.28 sobota","od":"10:45","do":"12:15","godziny":"2h00m","group_code":"","przedmiot":"Metodologia badań komunikacji społecznej i mediów","typ":"Wyk","sala":"S55 27-AULA","prowadzacy":"dr Magdalena Parus-Jankowska","zaliczenie":"Zaliczenie ocena","uwagi":"Brak"},{"data":"2026.02.28 sobota","od":"12:30","do":"14:00","godziny":"2h00m","group_code":"","przedmiot":"Koncepcje zarządzania","typ":"Wyk","sala":"S55 27-AULA","prowadzacy":"dr inż. Joanna Nowicka","zaliczenie":"Egzamin","uwagi":"Brak"},{"data":"2026.02.28 sobota","od":"14:15","do":"15:45","godziny":"2h00m","group_code":"","przedmiot":"Koncepcje zarządzania","typ":"Wyk","sala":"S55 27-AULA","prowadzacy":"dr inż. Joanna Nowicka","zaliczenie":"Egzamin","uwagi":"Brak"},{"data":"2026.02.28 sobota","od":"16:00","do":"17:30","godziny":"2h00m","group_code":"2","przedmiot":"Modelowanie 3D","typ":"Cw","sala":"S47 208","prowadzacy":"mgr Kacper Korzybski","zaliczenie":"Zaliczenie ocena","uwagi":"Brak"},{"data":"2026.02.28 sobota","od":"16:00","do":"17:30","godziny":"2h00m","group_code":"1","przedmiot":"Modelowanie 3D","typ":"Cw","sala":"S47 217","prowadzacy":"mgr Wojciech Jarosz","zaliczenie":"Zaliczenie ocena","uwagi":"Brak"},{"data":"2026.02.28 sobota","od":"17:40","do":"19:10","godziny":"2h00m","group_code":"1","przedmiot":"Modelowanie 3D","typ":"Cw","sala":"S47 217","prowadzacy":"mgr Wojciech Jarosz","zaliczenie":"Zaliczenie ocena","uwagi":"Brak"},{"data":"2026.02.28 sobota","od":"17:45","do":"19:15","godziny":"2h00m","group_code":"2","przedmiot":"Modelowanie 3D","typ":"Cw","sala":"S47 208","prowadzacy":"mgr Kacper Korzybski","zaliczenie":"Zaliczenie ocena","uwagi":"Brak"},{"data":"2026.02.28 sobota","od":"19:15","do":"20:00","godziny":"1h00m","group_code":"1","przedmiot":"Modelowanie 3D","typ":"Cw","sala":"S47 217","prowadzacy":"mgr Wojciech Jarosz","zaliczenie":"Zaliczenie ocena","uwagi":"Brak"},{"data":"2026.03.01 niedziela","od":"8:00","do":"8:45","godziny":"1h00m","group_code":"2","przedmiot":"Sculpting 3D","typ":"Cw","sala":"S55 16","prowadzacy":"mgr Tomasz Wojciechowski","zaliczenie":"Zaliczenie ocena","uwagi":"Brak"},{"data":"2026.03.01 niedziela","od":"8:00","do":"8:45","godziny":"1h00m","group_code":"1","przedmiot":"Motion design","typ":"Cw","sala":"S47 208","prowadzacy":"mgr Adrianna Kaim","zaliczenie":"Zaliczenie ocena","uwagi":"Brak"},{"data":"2026.03.01 niedziela","od":"9:00","do":"10:30","godziny":"2h00m","group_code":"2","przedmiot":"Sculpting 3D","typ":"Cw","sala":"S55 16","prowadzacy":"mgr Tomasz Wojciechowski","zaliczenie":"Zaliczenie ocena","uwagi":"Brak"},{"data":"2026.03.01 niedziela","od":"9:00","do":"10:30","godziny":"2h00m","group_code":"1","przedmiot":"Motion design","typ":"Cw","sala":"S47 208","prowadzacy":"mgr Adrianna Kaim","zaliczenie":"Zaliczenie ocena","uwagi":"Brak"},{"data":"2026.03.01 niedziela","od":"10:45","do":"12:15","godziny":"2h00m","group_code":"1","przedmiot":"Motion design","typ":"Cw","sala":"S47 208","prowadzacy":"mgr Adrianna Kaim","zaliczenie":"Zaliczenie ocena","uwagi":"Brak"},{"data":"2026.03.01 niedziela","od":"10:45","do":"12:15","godziny":"2h00m","group_code":"2","przedmiot":"Sculpting 3D","typ":"Cw","sala":"S55 16","prowadzacy":"mgr Tomasz Wojciechowski","zaliczenie":"Zaliczenie ocena","uwagi":"Brak"},{"data":"2026.03.01 niedziela","od":"12:30","do":"14:00","godziny":"2h00m","group_code":"2","przedmiot":"Motion design","typ":"Cw","sala":"S47 208","prowadzacy":"mgr Adrianna Kaim","zaliczenie":"Zaliczenie ocena","uwagi":"Brak"},{"data":"2026.03.01 niedziela","od":"12:30","do":"14:00","godziny":"2h00m","group_code":"1","przedmiot":"Sculpting 3D","typ":"Cw","sala":"S55 16","prowadzacy":"mgr Tomasz Wojciechowski","zaliczenie":"Zaliczenie ocena","uwagi":"Brak"},{"data":"2026.03.01 niedziela","od":"14:15","do":"15:45","godziny":"2h00m","group_code":"2","przedmiot":"Motion design","typ":"Cw","sala":"S47 208","prowadzacy":"mgr Adrianna Kaim","zaliczenie":"Zaliczenie ocena","uwagi":"Brak"},{"data":"2026.03.01 niedziela","od":"14:15","do":"15:45","godziny":"2h00m","group_code":"1","przedmiot":"Sculpting 3D","typ":"Cw","sala":"S55 16","prowadzacy":"mgr Tomasz Wojciechowski","zaliczenie":"Zaliczenie ocena","uwagi":"Brak"},{"data":"2026.03.01 niedziela","od":"16:00","do":"17:30","godziny":"2h00m","group_code":"","przedmiot":"Teoria nowych mediów","typ":"Wyk","sala":"S55 27-AULA","prowadzacy":"dr Ewa Kędzia","zaliczenie":"Egzamin","uwagi":"Brak"},{"data":"2026.03.01 niedziela","od":"17:45","do":"19:15","godziny":"2h00m","group_code":"","przedmiot":"Teoria nowych mediów","typ":"Wyk","sala":"S55 27-AULA","prowadzacy":"dr Ewa Kędzia","zaliczenie":"Egzamin","uwagi":"Brak"},{"data":"2026.03.14 sobota","od":"8:00","do":"8:45","godziny":"1h00m","group_code":"1","przedmiot":"Zajęcia z tutorem","typ":"Cw","sala":"S47 116","prowadzacy":"mgr Hanna Pachurka","zaliczenie":"Nie dotyczy","uwagi":"Brak"},{"data":"2026.03.14 sobota","od":"8:00","do":"8:45","godziny":"1h00m","group_code":"2","przedmiot":"Modelowanie 3D","typ":"Cw","sala":"S47 217","prowadzacy":"mgr Kacper Korzybski","zaliczenie":"Zaliczenie ocena","uwagi":"Brak"},{"data":"2026.03.14 sobota","od":"9:00","do":"10:30","godziny":"2h00m","group_code":"1","przedmiot":"Wprowadzenie do Specjalnościowej praktyki zawodowej 1","typ":"Cw","sala":"S47 116","prowadzacy":"mgr Hanna Pachurka","zaliczenie":"Nie dotyczy","uwagi":"Brak"},{"data":"2026.03.14 sobota","od":"9:00","do":"10:30","godziny":"2h00m","group_code":"2","przedmiot":"Modelowanie 3D","typ":"Cw","sala":"S47 217","prowadzacy":"mgr Kacper Korzybski","zaliczenie":"Zaliczenie ocena","uwagi":"Brak"},{"data":"2026.03.14 sobota","od":"10:45","do":"12:15","godziny":"2h00m","group_code":"2","przedmiot":"Modelowanie 3D","typ":"Cw","sala":"S47 217","prowadzacy":"mgr Kacper Korzybski","zaliczenie":"Zaliczenie ocena","uwagi":"Brak"},{"data":"2026.03.14 sobota","od":"10:45","do":"12:15","godziny":"2h00m","group_code":"1","przedmiot":"Self-branding i zarządzanie marką osobistą","typ":"Cw","sala":"S47 119","prowadzacy":"mgr Oliwia Świątek","zaliczenie":"Zaliczenie ocena","uwagi":"Brak"},{"data":"2026.03.14 sobota","od":"12:30","do":"14:00","godziny":"2h00m","group_code":"2","przedmiot":"Modelowanie 3D","typ":"Cw","sala":"S47 217","prowadzacy":"mgr Kacper Korzybski","zaliczenie":"Zaliczenie ocena","uwagi":"Brak"},{"data":"2026.03.14 sobota","od":"14:15","do":"15:45","godziny":"2h00m","group_code":"1","przedmiot":"Modelowanie 3D","typ":"Cw","sala":"S55 107","prowadzacy":"mgr Kacper Korzybski","zaliczenie":"Zaliczenie ocena","uwagi":"Brak"},{"data":"2026.03.14 sobota","od":"14:15","do":"15:45","godziny":"2h00m","group_code":"2","przedmiot":"Metodologia badań komunikacji społecznej i mediów","typ":"Cw","sala":"S47 116","prowadzacy":"dr Magdalena Parus-Jankowska","zaliczenie":"Zaliczenie ocena","uwagi":"Brak"},{"data":"2026.03.14 sobota","od":"15:55","do":"17:25","godziny":"2h00m","group_code":"2","przedmiot":"Metodologia badań komunikacji społecznej i mediów","typ":"Cw","sala":"S47 116","prowadzacy":"dr Magdalena Parus-Jankowska","zaliczenie":"Zaliczenie ocena","uwagi":"Brak"},{"data":"2026.03.14 sobota","od":"16:00","do":"18:15","godziny":"3h00m","group_code":"1","przedmiot":"Modelowanie 3D","typ":"Cw","sala":"S55 107","prowadzacy":"mgr Kacper Korzybski","zaliczenie":"Zaliczenie ocena","uwagi":"Brak"},{"data":"2026.03.14 sobota","od":"17:35","do":"19:05","godziny":"2h00m","group_code":"2","przedmiot":"Wprowadzenie do Specjalnościowej praktyki zawodowej 1","typ":"Cw","sala":"S47 116","prowadzacy":"mgr Hanna Pachurka","zaliczenie":"Nie dotyczy","uwagi":"Brak"},{"data":"2026.03.14 sobota","od":"19:10","do":"19:55","godziny":"1h00m","group_code":"2","przedmiot":"Zajęcia z tutorem","typ":"Cw","sala":"S47 116","prowadzacy":"mgr Hanna Pachurka","zaliczenie":"Nie dotyczy","uwagi":"Brak"},{"data":"2026.03.15 niedziela","od":"8:00","do":"10:30","godziny":"3h00m","group_code":"2","przedmiot":"Koncepcje zarządzania","typ":"Cw","sala":"S47 308","prowadzacy":"dr inż. Joanna Nowicka","zaliczenie":"Zaliczenie ocena","uwagi":"Brak"},{"data":"2026.03.15 niedziela","od":"10:45","do":"12:15","godziny":"2h00m","group_code":"2","przedmiot":"Koncepcje zarządzania","typ":"Cw","sala":"S47 308","prowadzacy":"dr inż. Joanna Nowicka","zaliczenie":"Zaliczenie ocena","uwagi":"Brak"},{"data":"2026.03.15 niedziela","od":"12:30","do":"14:00","godziny":"2h00m","group_code":"1","przedmiot":"Koncepcje zarządzania","typ":"Cw","sala":"W12 20","prowadzacy":"dr inż. Joanna Nowicka","zaliczenie":"Zaliczenie ocena","uwagi":"Brak"},{"data":"2026.03.15 niedziela","od":"14:15","do":"15:45","godziny":"2h00m","group_code":"1","przedmiot":"Koncepcje zarządzania","typ":"Cw","sala":"W12 20","prowadzacy":"dr inż. Joanna Nowicka","zaliczenie":"Zaliczenie ocena","uwagi":"Brak"},{"data":"2026.03.15 niedziela","od":"16:00","do":"16:45","godziny":"1h00m","group_code":"1","przedmiot":"Koncepcje zarządzania","typ":"Cw","sala":"W12 20","prowadzacy":"dr inż. Joanna Nowicka","zaliczenie":"Zaliczenie ocena","uwagi":"Brak"},{"data":"2026.03.28 sobota","od":"8:00","do":"8:45","godziny":"1h00m","group_code":"1","przedmiot":"Texturowanie, mapowanie i shading","typ":"Cw","sala":"S55 16","prowadzacy":"mgr Wojciech Jarosz","zaliczenie":"Zaliczenie ocena","uwagi":"Brak"},{"data":"2026.03.28 sobota","od":"8:00","do":"8:45","godziny":"1h00m","group_code":"2","przedmiot":"Modelowanie 3D","typ":"Cw","sala":"S47 217","prowadzacy":"mgr Kacper Korzybski","zaliczenie":"Zaliczenie ocena","uwagi":"Brak"},{"data":"2026.03.28 sobota","od":"9:00","do":"10:30","godziny":"2h00m","group_code":"2","przedmiot":"Modelowanie 3D","typ":"Cw","sala":"S47 217","prowadzacy":"mgr Kacper Korzybski","zaliczenie":"Zaliczenie ocena","uwagi":"Brak"},{"data":"2026.03.28 sobota","od":"9:00","do":"10:30","godziny":"2h00m","group_code":"1","przedmiot":"Texturowanie, mapowanie i shading","typ":"Cw","sala":"S55 16","prowadzacy":"mgr Wojciech Jarosz","zaliczenie":"Zaliczenie ocena","uwagi":"Brak"},{"data":"2026.03.28 sobota","od":"10:45","do":"12:15","godziny":"2h00m","group_code":"2","przedmiot":"Modelowanie 3D","typ":"Cw","sala":"S47 217","prowadzacy":"mgr Kacper Korzybski","zaliczenie":"Zaliczenie ocena","uwagi":"Brak"},{"data":"2026.03.28 sobota","od":"10:45","do":"12:15","godziny":"2h00m","group_code":"1","przedmiot":"Texturowanie, mapowanie i shading","typ":"Cw","sala":"S55 16","prowadzacy":"mgr Wojciech Jarosz","zaliczenie":"Zaliczenie ocena","uwagi":"Brak"},{"data":"2026.03.28 sobota","od":"12:30","do":"14:00","godziny":"2h00m","group_code":"1","przedmiot":"Metodologia badań komunikacji społecznej i mediów","typ":"Cw","sala":"W12 18","prowadzacy":"dr Magdalena Parus-Jankowska","zaliczenie":"Zaliczenie ocena","uwagi":"Brak"},{"data":"2026.03.28 sobota","od":"12:30","do":"14:00","godziny":"2h00m","group_code":"2","przedmiot":"Texturowanie, mapowanie i shading","typ":"Cw","sala":"S55 16","prowadzacy":"mgr Wojciech Jarosz","zaliczenie":"Zaliczenie ocena","uwagi":"Brak"},{"data":"2026.03.28 sobota","od":"14:15","do":"15:45","godziny":"2h00m","group_code":"1","przedmiot":"Metodologia badań komunikacji społecznej i mediów","typ":"Cw","sala":"W12 18","prowadzacy":"dr Magdalena Parus-Jankowska","zaliczenie":"Zaliczenie ocena","uwagi":"Brak"},{"data":"2026.03.28 sobota","od":"14:15","do":"15:45","godziny":"2h00m","group_code":"2","przedmiot":"Texturowanie, mapowanie i shading","typ":"Cw","sala":"S55 16","prowadzacy":"mgr Wojciech Jarosz","zaliczenie":"Zaliczenie ocena","uwagi":"Brak"},{"data":"2026.03.28 sobota","od":"16:00","do":"17:30","godziny":"2h00m","group_code":"1","przedmiot":"Modelowanie 3D","typ":"Cw","sala":"S55 16","prowadzacy":"mgr Wojciech Jarosz","zaliczenie":"Zaliczenie ocena","uwagi":"Brak"},{"data":"2026.03.28 sobota","od":"17:45","do":"19:15","godziny":"2h00m","group_code":"1","przedmiot":"Modelowanie 3D","typ":"Cw","sala":"S55 16","prowadzacy":"mgr Wojciech Jarosz","zaliczenie":"Zaliczenie ocena","uwagi":"Brak"},{"data":"2026.03.28 sobota","od":"19:30","do":"20:15","godziny":"1h00m","group_code":"1","przedmiot":"Modelowanie 3D","typ":"Cw","sala":"S55 16","prowadzacy":"mgr Wojciech Jarosz","zaliczenie":"Zaliczenie ocena","uwagi":"Brak"},{"data":"2026.03.29 niedziela","od":"8:00","do":"8:45","godziny":"1h00m","group_code":"2","przedmiot":"Motion design","typ":"Cw","sala":"S47 208","prowadzacy":"mgr Adrianna Kaim","zaliczenie":"Zaliczenie ocena","uwagi":"Brak"},{"data":"2026.03.29 niedziela","od":"8:00","do":"8:45","godziny":"1h00m","group_code":"1","przedmiot":"Sculpting 3D","typ":"Cw","sala":"S47 216","prowadzacy":"mgr Tomasz Wojciechowski","zaliczenie":"Zaliczenie ocena","uwagi":"Brak"},{"data":"2026.03.29 niedziela","od":"9:00","do":"10:30","godziny":"2h00m","group_code":"2","przedmiot":"Motion design","typ":"Cw","sala":"S47 208","prowadzacy":"mgr Adrianna Kaim","zaliczenie":"Zaliczenie ocena","uwagi":"Brak"},{"data":"2026.03.29 niedziela","od":"9:00","do":"10:30","godziny":"2h00m","group_code":"1","przedmiot":"Sculpting 3D","typ":"Cw","sala":"S47 216","prowadzacy":"mgr Tomasz Wojciechowski","zaliczenie":"Zaliczenie ocena","uwagi":"Brak"},{"data":"2026.03.29 niedziela","od":"10:45","do":"12:15","godziny":"2h00m","group_code":"1","przedmiot":"Sculpting 3D","typ":"Cw","sala":"S47 216","prowadzacy":"mgr Tomasz Wojciechowski","zaliczenie":"Zaliczenie ocena","uwagi":"Brak"},{"data":"2026.03.29 niedziela","od":"10:45","do":"12:15","godziny":"2h00m","group_code":"2","przedmiot":"Motion design","typ":"Cw","sala":"S47 208","prowadzacy":"mgr Adrianna Kaim","zaliczenie":"Zaliczenie ocena","uwagi":"Brak"},{"data":"2026.03.29 niedziela","od":"12:30","do":"14:00","godziny":"2h00m","group_code":"1","przedmiot":"Motion design","typ":"Cw","sala":"S47 216","prowadzacy":"mgr Adrianna Kaim","zaliczenie":"Zaliczenie ocena","uwagi":"Brak"},{"data":"2026.03.29 niedziela","od":"12:30","do":"14:00","godziny":"2h00m","group_code":"2","przedmiot":"Sculpting 3D","typ":"Cw","sala":"S55 16","prowadzacy":"mgr Tomasz Wojciechowski","zaliczenie":"Zaliczenie ocena","uwagi":"Brak"},{"data":"2026.03.29 niedziela","od":"14:15","do":"15:45","godziny":"2h00m","group_code":"2","przedmiot":"Sculpting 3D","typ":"Cw","sala":"S55 16","prowadzacy":"mgr Tomasz Wojciechowski","zaliczenie":"Zaliczenie ocena","uwagi":"Brak"},{"data":"2026.03.29 niedziela","od":"14:15","do":"15:45","godziny":"2h00m","group_code":"1","przedmiot":"Motion design","typ":"Cw","sala":"S47 216","prowadzacy":"mgr Adrianna Kaim","zaliczenie":"Zaliczenie ocena","uwagi":"Brak"},{"data":"2026.03.29 niedziela","od":"16:00","do":"17:30","godziny":"2h00m","group_code":"1","przedmiot":"Modelowanie 3D","typ":"Cw","sala":"S47 216","prowadzacy":"mgr Kacper Korzybski","zaliczenie":"Zaliczenie ocena","uwagi":"Brak"},{"data":"2026.03.29 niedziela","od":"16:00","do":"17:30","godziny":"2h00m","group_code":"2","przedmiot":"Sculpting 3D","typ":"Cw","sala":"S55 16","prowadzacy":"mgr Tomasz Wojciechowski","zaliczenie":"Zaliczenie ocena","uwagi":"Brak"},{"data":"2026.03.29 niedziela","od":"17:40","do":"19:55","godziny":"3h00m","group_code":"","przedmiot":"Koncepcje zarządzania","typ":"Wyk","sala":"S55 27-AULA","prowadzacy":"dr inż. Joanna Nowicka","zaliczenie":"Egzamin","uwagi":"Brak"},{"data":"2026.04.18 sobota","od":"8:00","do":"8:45","godziny":"1h00m","group_code":"1","przedmiot":"Modelowanie 3D","typ":"Cw","sala":"S55 106","prowadzacy":"mgr Wojciech Jarosz","zaliczenie":"Zaliczenie ocena","uwagi":"Brak"},{"data":"2026.04.18 sobota","od":"9:00","do":"10:30","godziny":"2h00m","group_code":"2","przedmiot":"Modelowanie 3D","typ":"Cw","sala":"S55 308","prowadzacy":"mgr Kacper Korzybski","zaliczenie":"Zaliczenie ocena","uwagi":"Brak"},{"data":"2026.04.18 sobota","od":"9:00","do":"10:30","godziny":"2h00m","group_code":"1","przedmiot":"Modelowanie 3D","typ":"Cw","sala":"S55 106","prowadzacy":"mgr Wojciech Jarosz","zaliczenie":"Zaliczenie ocena","uwagi":"Brak"},{"data":"2026.04.18 sobota","od":"10:45","do":"12:15","godziny":"2h00m","group_code":"2","przedmiot":"Modelowanie 3D","typ":"Cw","sala":"S55 308","prowadzacy":"mgr Kacper Korzybski","zaliczenie":"Zaliczenie ocena","uwagi":"Brak"},{"data":"2026.04.18 sobota","od":"10:45","do":"12:15","godziny":"2h00m","group_code":"1","przedmiot":"Modelowanie 3D","typ":"Cw","sala":"S55 106","prowadzacy":"mgr Wojciech Jarosz","zaliczenie":"Zaliczenie ocena","uwagi":"Brak"},{"data":"2026.04.18 sobota","od":"12:30","do":"14:00","godziny":"2h00m","group_code":"1","przedmiot":"Modelowanie 3D","typ":"Cw","sala":"S55 106","prowadzacy":"mgr Wojciech Jarosz","zaliczenie":"Zaliczenie ocena","uwagi":"Brak"},{"data":"2026.04.18 sobota","od":"12:30","do":"14:00","godziny":"2h00m","group_code":"2","przedmiot":"Modelowanie 3D","typ":"Cw","sala":"S55 308","prowadzacy":"mgr Kacper Korzybski","zaliczenie":"Zaliczenie ocena","uwagi":"Brak"},{"data":"2026.04.18 sobota","od":"14:15","do":"15:45","godziny":"2h00m","group_code":"2","przedmiot":"Metodologia badań komunikacji społecznej i mediów","typ":"Cw","sala":"S47 116","prowadzacy":"dr Magdalena Parus-Jankowska","zaliczenie":"Zaliczenie ocena","uwagi":"Brak"},{"data":"2026.04.18 sobota","od":"14:15","do":"15:45","godziny":"2h00m","group_code":"1","przedmiot":"Texturowanie, mapowanie i shading","typ":"Cw","sala":"S55 16","prowadzacy":"mgr Wojciech Jarosz","zaliczenie":"Zaliczenie ocena","uwagi":"Brak"},{"data":"2026.04.18 sobota","od":"16:00","do":"17:30","godziny":"2h00m","group_code":"2","przedmiot":"Metodologia badań komunikacji społecznej i mediów","typ":"Cw","sala":"S47 116","prowadzacy":"dr Magdalena Parus-Jankowska","zaliczenie":"Zaliczenie ocena","uwagi":"Brak"},{"data":"2026.04.18 sobota","od":"16:00","do":"17:30","godziny":"2h00m","group_code":"1","przedmiot":"Texturowanie, mapowanie i shading","typ":"Cw","sala":"S55 16","prowadzacy":"mgr Wojciech Jarosz","zaliczenie":"Zaliczenie ocena","uwagi":"Brak"},{"data":"2026.04.18 sobota","od":"17:40","do":"19:55","godziny":"3h00m","group_code":"","przedmiot":"Koncepcje zarządzania","typ":"Wyk","sala":"S55 27-AULA","prowadzacy":"dr inż. Joanna Nowicka","zaliczenie":"Egzamin","uwagi":"Brak"},{"data":"2026.04.18 sobota","od":"17:45","do":"18:30","godziny":"1h00m","group_code":"1","przedmiot":"Texturowanie, mapowanie i shading","typ":"Cw","sala":"S55 16","prowadzacy":"mgr Wojciech Jarosz","zaliczenie":"Zaliczenie ocena","uwagi":"Brak"},{"data":"2026.04.19 niedziela","od":"9:00","do":"10:30","godziny":"2h00m","group_code":"2","przedmiot":"Self-branding i zarządzanie marką osobistą","typ":"Cw","sala":"S47 124","prowadzacy":"mgr Oliwia Świątek","zaliczenie":"Zaliczenie ocena","uwagi":"Brak"},{"data":"2026.04.19 niedziela","od":"10:45","do":"12:15","godziny":"2h00m","group_code":"2","przedmiot":"Koncepcje zarządzania","typ":"Cw","sala":"S47 212 - prac. matematyczna/ratownicza","prowadzacy":"dr inż. Joanna Nowicka","zaliczenie":"Zaliczenie ocena","uwagi":"Brak"},{"data":"2026.04.19 niedziela","od":"12:30","do":"14:00","godziny":"2h00m","group_code":"2","przedmiot":"Modelowanie 3D","typ":"Cw","sala":"S47 217","prowadzacy":"mgr Kacper Korzybski","zaliczenie":"Zaliczenie ocena","uwagi":"Brak"},{"data":"2026.04.19 niedziela","od":"14:15","do":"15:45","godziny":"2h00m","group_code":"2","przedmiot":"Modelowanie 3D","typ":"Cw","sala":"S47 217","prowadzacy":"mgr Kacper Korzybski","zaliczenie":"Zaliczenie ocena","uwagi":"Brak"},{"data":"2026.04.19 niedziela","od":"14:15","do":"15:45","godziny":"2h00m","group_code":"1","przedmiot":"Metodologia badań komunikacji społecznej i mediów","typ":"Cw","sala":"S47 119","prowadzacy":"dr Magdalena Parus-Jankowska","zaliczenie":"Zaliczenie ocena","uwagi":"Brak"},{"data":"2026.04.19 niedziela","od":"16:00","do":"17:30","godziny":"2h00m","group_code":"2","przedmiot":"Modelowanie 3D","typ":"Cw","sala":"S47 217","prowadzacy":"mgr Kacper Korzybski","zaliczenie":"Zaliczenie ocena","uwagi":"Brak"},{"data":"2026.04.19 niedziela","od":"16:00","do":"17:30","godziny":"2h00m","group_code":"1","przedmiot":"Metodologia badań komunikacji społecznej i mediów","typ":"Cw","sala":"S47 119","prowadzacy":"dr Magdalena Parus-Jankowska","zaliczenie":"Zaliczenie ocena","uwagi":"Brak"},{"data":"2026.04.19 niedziela","od":"17:45","do":"19:15","godziny":"2h00m","group_code":"1","przedmiot":"Koncepcje zarządzania","typ":"Cw","sala":"S47 120","prowadzacy":"dr inż. Joanna Nowicka","zaliczenie":"Zaliczenie ocena","uwagi":"Brak"},{"data":"2026.05.09 sobota","od":"8:00","do":"8:45","godziny":"1h00m","group_code":"2","przedmiot":"Koncepcje zarządzania","typ":"Cw","sala":"W12 30","prowadzacy":"dr inż. Joanna Nowicka","zaliczenie":"Zaliczenie ocena","uwagi":"Brak"},{"data":"2026.05.09 sobota","od":"9:00","do":"10:30","godziny":"2h00m","group_code":"2","przedmiot":"Koncepcje zarządzania","typ":"Cw","sala":"W12 30","prowadzacy":"dr inż. Joanna Nowicka","zaliczenie":"Zaliczenie ocena","uwagi":"Brak"},{"data":"2026.05.09 sobota","od":"9:00","do":"10:30","godziny":"2h00m","group_code":"1","przedmiot":"Modelowanie 3D","typ":"Cw","sala":"S55 16","prowadzacy":"mgr Wojciech Jarosz","zaliczenie":"Zaliczenie ocena","uwagi":"Brak"},{"data":"2026.05.09 sobota","od":"10:45","do":"12:15","godziny":"2h00m","group_code":"2","przedmiot":"Koncepcje zarządzania","typ":"Cw","sala":"W12 30","prowadzacy":"dr inż. Joanna Nowicka","zaliczenie":"Zaliczenie ocena","uwagi":"Brak"},{"data":"2026.05.09 sobota","od":"10:45","do":"12:15","godziny":"2h00m","group_code":"1","przedmiot":"Modelowanie 3D","typ":"Cw","sala":"S55 16","prowadzacy":"mgr Wojciech Jarosz","zaliczenie":"Zaliczenie ocena","uwagi":"Brak"},{"data":"2026.05.09 sobota","od":"12:30","do":"14:00","godziny":"2h00m","group_code":"2","przedmiot":"Texturowanie, mapowanie i shading","typ":"Cw","sala":"S55 15","prowadzacy":"mgr Wojciech Jarosz","zaliczenie":"Zaliczenie ocena","uwagi":"Brak"},{"data":"2026.05.09 sobota","od":"13:15","do":"14:00","godziny":"1h00m","group_code":"1","przedmiot":"Koncepcje zarządzania","typ":"Cw","sala":"S47 312 - prac. matematyczna","prowadzacy":"dr inż. Joanna Nowicka","zaliczenie":"Zaliczenie ocena","uwagi":"Brak"},{"data":"2026.05.09 sobota","od":"14:15","do":"15:45","godziny":"2h00m","group_code":"2","przedmiot":"Texturowanie, mapowanie i shading","typ":"Cw","sala":"S55 15","prowadzacy":"mgr Wojciech Jarosz","zaliczenie":"Zaliczenie ocena","uwagi":"Brak"},{"data":"2026.05.09 sobota","od":"14:15","do":"15:45","godziny":"2h00m","group_code":"1","przedmiot":"Koncepcje zarządzania","typ":"Cw","sala":"S47 312 - prac. matematyczna","prowadzacy":"dr inż. Joanna Nowicka","zaliczenie":"Zaliczenie ocena","uwagi":"Brak"},{"data":"2026.05.09 sobota","od":"15:55","do":"17:25","godziny":"2h00m","group_code":"2","przedmiot":"Texturowanie, mapowanie i shading","typ":"Cw","sala":"S55 15","prowadzacy":"mgr Wojciech Jarosz","zaliczenie":"Zaliczenie ocena","uwagi":"Brak"},{"data":"2026.05.09 sobota","od":"15:55","do":"17:25","godziny":"2h00m","group_code":"1","przedmiot":"Koncepcje zarządzania","typ":"Cw","sala":"S47 312 - prac. matematyczna","prowadzacy":"dr inż. Joanna Nowicka","zaliczenie":"Zaliczenie ocena","uwagi":"Brak"},{"data":"2026.05.09 sobota","od":"17:35","do":"20:40","godziny":"4h00m","group_code":"1","przedmiot":"Texturowanie, mapowanie i shading","typ":"Cw","sala":"S55 15","prowadzacy":"mgr Wojciech Jarosz","zaliczenie":"Zaliczenie ocena","uwagi":"Brak"},{"data":"2026.05.10 niedziela","od":"8:00","do":"8:45","godziny":"1h00m","group_code":"1","przedmiot":"Motion design","typ":"Cw","sala":"S47 216","prowadzacy":"mgr Adrianna Kaim","zaliczenie":"Zaliczenie ocena","uwagi":"Brak"},{"data":"2026.05.10 niedziela","od":"8:00","do":"8:45","godziny":"1h00m","group_code":"2","przedmiot":"Sculpting 3D","typ":"Cw","sala":"S55 15","prowadzacy":"mgr Tomasz Wojciechowski","zaliczenie":"Zaliczenie ocena","uwagi":"Brak"},{"data":"2026.05.10 niedziela","od":"9:00","do":"10:30","godziny":"2h00m","group_code":"2","przedmiot":"Sculpting 3D","typ":"Cw","sala":"S55 15","prowadzacy":"mgr Tomasz Wojciechowski","zaliczenie":"Zaliczenie ocena","uwagi":"Brak"},{"data":"2026.05.10 niedziela","od":"9:00","do":"10:30","godziny":"2h00m","group_code":"1","przedmiot":"Motion design","typ":"Cw","sala":"S47 216","prowadzacy":"mgr Adrianna Kaim","zaliczenie":"Zaliczenie ocena","uwagi":"Brak"},{"data":"2026.05.10 niedziela","od":"10:45","do":"12:15","godziny":"2h00m","group_code":"2","przedmiot":"Sculpting 3D","typ":"Cw","sala":"S55 15","prowadzacy":"mgr Tomasz Wojciechowski","zaliczenie":"Zaliczenie ocena","uwagi":"Brak"},{"data":"2026.05.10 niedziela","od":"10:45","do":"12:15","godziny":"2h00m","group_code":"1","przedmiot":"Motion design","typ":"Cw","sala":"S47 216","prowadzacy":"mgr Adrianna Kaim","zaliczenie":"Zaliczenie ocena","uwagi":"Brak"},{"data":"2026.05.10 niedziela","od":"12:30","do":"14:00","godziny":"2h00m","group_code":"2","przedmiot":"Motion design","typ":"Cw","sala":"S47 216","prowadzacy":"mgr Adrianna Kaim","zaliczenie":"Zaliczenie ocena","uwagi":"Brak"},{"data":"2026.05.10 niedziela","od":"12:30","do":"14:00","godziny":"2h00m","group_code":"1","przedmiot":"Sculpting 3D","typ":"Cw","sala":"S55 15","prowadzacy":"mgr Tomasz Wojciechowski","zaliczenie":"Zaliczenie ocena","uwagi":"Brak"},{"data":"2026.05.10 niedziela","od":"14:15","do":"15:45","godziny":"2h00m","group_code":"1","przedmiot":"Sculpting 3D","typ":"Cw","sala":"S55 15","prowadzacy":"mgr Tomasz Wojciechowski","zaliczenie":"Zaliczenie ocena","uwagi":"Brak"},{"data":"2026.05.10 niedziela","od":"14:15","do":"15:45","godziny":"2h00m","group_code":"2","przedmiot":"Motion design","typ":"Cw","sala":"S47 216","prowadzacy":"mgr Adrianna Kaim","zaliczenie":"Zaliczenie ocena","uwagi":"Brak"},{"data":"2026.05.10 niedziela","od":"16:00","do":"17:30","godziny":"2h00m","group_code":"","przedmiot":"Metodologia badań komunikacji społecznej i mediów","typ":"Wyk","sala":"S55 27-AULA","prowadzacy":"dr Magdalena Parus-Jankowska","zaliczenie":"Zaliczenie ocena","uwagi":"Brak"},{"data":"2026.05.10 niedziela","od":"17:40","do":"19:55","godziny":"3h00m","group_code":"","przedmiot":"Metodologia badań komunikacji społecznej i mediów","typ":"Wyk","sala":"S55 27-AULA","prowadzacy":"dr Magdalena Parus-Jankowska","zaliczenie":"Zaliczenie ocena","uwagi":"Brak"},{"data":"2026.05.16 sobota","od":"8:00","do":"8:45","godziny":"1h00m","group_code":"","przedmiot":"Koncepcje zarządzania","typ":"Wyk","sala":"","prowadzacy":"dr inż. Joanna Nowicka","zaliczenie":"Egzamin","uwagi":"Distance learning"},{"data":"2026.05.16 sobota","od":"9:00","do":"10:30","godziny":"2h00m","group_code":"","przedmiot":"Koncepcje zarządzania","typ":"Wyk","sala":"","prowadzacy":"dr inż. Joanna Nowicka","zaliczenie":"Egzamin","uwagi":"Distance learning"},{"data":"2026.05.16 sobota","od":"10:45","do":"12:15","godziny":"2h00m","group_code":"","przedmiot":"Koncepcje zarządzania","typ":"Wyk","sala":"","prowadzacy":"dr inż. Joanna Nowicka","zaliczenie":"Egzamin","uwagi":"Distance learning"},{"data":"2026.05.16 sobota","od":"12:30","do":"14:00","godziny":"2h00m","group_code":"1","przedmiot":"Self-branding i zarządzanie marką osobistą","typ":"Cw","sala":"","prowadzacy":"mgr Oliwia Świątek","zaliczenie":"Zaliczenie ocena","uwagi":"Distance learning"},{"data":"2026.05.16 sobota","od":"14:15","do":"15:45","godziny":"2h00m","group_code":"","przedmiot":"Teoria nowych mediów","typ":"Wyk","sala":"","prowadzacy":"dr Ewa Kędzia","zaliczenie":"Egzamin","uwagi":"Distance learning"},{"data":"2026.05.16 sobota","od":"16:00","do":"17:30","godziny":"2h00m","group_code":"","przedmiot":"Teoria nowych mediów","typ":"Wyk","sala":"","prowadzacy":"dr Ewa Kędzia","zaliczenie":"Egzamin","uwagi":"Distance learning"},{"data":"2026.05.16 sobota","od":"17:45","do":"19:15","godziny":"2h00m","group_code":"","przedmiot":"Teoria nowych mediów","typ":"Wyk","sala":"","prowadzacy":"dr Ewa Kędzia","zaliczenie":"Egzamin","uwagi":"Distance learning"},{"data":"2026.05.17 niedziela","od":"8:00","do":"8:45","godziny":"1h00m","group_code":"2","przedmiot":"Self-branding i zarządzanie marką osobistą","typ":"Cw","sala":"","prowadzacy":"mgr Oliwia Świątek","zaliczenie":"Zaliczenie ocena","uwagi":"Distance learning"},{"data":"2026.05.17 niedziela","od":"9:00","do":"10:30","godziny":"2h00m","group_code":"2","przedmiot":"Self-branding i zarządzanie marką osobistą","typ":"Cw","sala":"","prowadzacy":"mgr Oliwia Świątek","zaliczenie":"Zaliczenie ocena","uwagi":"Distance learning"},{"data":"2026.05.17 niedziela","od":"10:45","do":"12:15","godziny":"2h00m","group_code":"2","przedmiot":"Self-branding i zarządzanie marką osobistą","typ":"Cw","sala":"","prowadzacy":"mgr Oliwia Świątek","zaliczenie":"Zaliczenie ocena","uwagi":"Distance learning"},{"data":"2026.05.30 sobota","od":"9:00","do":"10:30","godziny":"2h00m","group_code":"2","przedmiot":"Texturowanie, mapowanie i shading","typ":"Cw","sala":"S55 16","prowadzacy":"mgr Wojciech Jarosz","zaliczenie":"Zaliczenie ocena","uwagi":"Brak"},{"data":"2026.05.30 sobota","od":"10:45","do":"12:15","godziny":"2h00m","group_code":"1","przedmiot":"Sculpting 3D","typ":"Cw","sala":"S55 107","prowadzacy":"mgr Tomasz Wojciechowski","zaliczenie":"Zaliczenie ocena","uwagi":"Brak"},{"data":"2026.05.30 sobota","od":"10:45","do":"12:15","godziny":"2h00m","group_code":"2","przedmiot":"Texturowanie, mapowanie i shading","typ":"Cw","sala":"S55 16","prowadzacy":"mgr Wojciech Jarosz","zaliczenie":"Zaliczenie ocena","uwagi":"Brak"},{"data":"2026.05.30 sobota","od":"12:30","do":"14:00","godziny":"2h00m","group_code":"2","przedmiot":"Texturowanie, mapowanie i shading","typ":"Cw","sala":"S55 16","prowadzacy":"mgr Wojciech Jarosz","zaliczenie":"Zaliczenie ocena","uwagi":"Brak"},{"data":"2026.05.30 sobota","od":"12:30","do":"14:00","godziny":"2h00m","group_code":"1","przedmiot":"Sculpting 3D","typ":"Cw","sala":"S55 107","prowadzacy":"mgr Tomasz Wojciechowski","zaliczenie":"Zaliczenie ocena","uwagi":"Brak"},{"data":"2026.05.30 sobota","od":"14:15","do":"15:45","godziny":"2h00m","group_code":"1","przedmiot":"Texturowanie, mapowanie i shading","typ":"Cw","sala":"S55 16","prowadzacy":"mgr Wojciech Jarosz","zaliczenie":"Zaliczenie ocena","uwagi":"Brak"},{"data":"2026.05.30 sobota","od":"14:15","do":"15:45","godziny":"2h00m","group_code":"2","przedmiot":"Sculpting 3D","typ":"Cw","sala":"S55 106","prowadzacy":"mgr Tomasz Wojciechowski","zaliczenie":"Zaliczenie ocena","uwagi":"Brak"},{"data":"2026.05.30 sobota","od":"16:00","do":"17:30","godziny":"2h00m","group_code":"2","przedmiot":"Sculpting 3D","typ":"Cw","sala":"S55 106","prowadzacy":"mgr Tomasz Wojciechowski","zaliczenie":"Zaliczenie ocena","uwagi":"Brak"},{"data":"2026.05.30 sobota","od":"16:00","do":"17:30","godziny":"2h00m","group_code":"1","przedmiot":"Modelowanie 3D","typ":"Cw","sala":"S55 16","prowadzacy":"mgr Wojciech Jarosz","zaliczenie":"Zaliczenie ocena","uwagi":"Brak"},{"data":"2026.05.30 sobota","od":"17:45","do":"19:15","godziny":"2h00m","group_code":"1","przedmiot":"Modelowanie 3D","typ":"Cw","sala":"S55 16","prowadzacy":"mgr Wojciech Jarosz","zaliczenie":"Zaliczenie ocena","uwagi":"Brak"},{"data":"2026.05.30 sobota","od":"19:30","do":"20:15","godziny":"1h00m","group_code":"1","przedmiot":"Modelowanie 3D","typ":"Cw","sala":"S55 16","prowadzacy":"mgr Wojciech Jarosz","zaliczenie":"Zaliczenie ocena","uwagi":"Brak"},{"data":"2026.05.31 niedziela","od":"10:45","do":"12:15","godziny":"2h00m","group_code":"2","przedmiot":"Metodologia badań komunikacji społecznej i mediów","typ":"Cw","sala":"S55 108","prowadzacy":"dr Magdalena Parus-Jankowska","zaliczenie":"Zaliczenie ocena","uwagi":"Brak"},{"data":"2026.05.31 niedziela","od":"12:30","do":"14:00","godziny":"2h00m","group_code":"2","przedmiot":"Metodologia badań komunikacji społecznej i mediów","typ":"Cw","sala":"S55 108","prowadzacy":"dr Magdalena Parus-Jankowska","zaliczenie":"Zaliczenie ocena","uwagi":"Brak"},{"data":"2026.05.31 niedziela","od":"15:00","do":"15:45","godziny":"1h00m","group_code":"","przedmiot":"Teoria nowych mediów","typ":"Wyk","sala":"S55 27-AULA","prowadzacy":"dr Ewa Kędzia","zaliczenie":"Egzamin","uwagi":"Brak"},{"data":"2026.05.31 niedziela","od":"16:00","do":"17:30","godziny":"2h00m","group_code":"","przedmiot":"Teoria nowych mediów","typ":"Wyk","sala":"S55 27-AULA","prowadzacy":"dr Ewa Kędzia","zaliczenie":"Egzamin","uwagi":"Brak"},{"data":"2026.05.31 niedziela","od":"17:45","do":"19:15","godziny":"2h00m","group_code":"","przedmiot":"Teoria nowych mediów","typ":"Wyk","sala":"S55 27-AULA","prowadzacy":"dr Ewa Kędzia","zaliczenie":"Egzamin","uwagi":"Brak"},{"data":"2026.05.31 niedziela","od":"18:30","do":"20:15","godziny":"2h00m","group_code":"1","przedmiot":"Motion design","typ":"Cw","sala":"S55 16","prowadzacy":"mgr Adrianna Kaim","zaliczenie":"Zaliczenie ocena","uwagi":"Brak"},{"data":"2026.06.13 sobota","od":"8:00","do":"8:45","godziny":"1h00m","group_code":"2","przedmiot":"Self-branding i zarządzanie marką osobistą","typ":"Cw","sala":"S47 120","prowadzacy":"mgr Oliwia Świątek","zaliczenie":"Zaliczenie ocena","uwagi":"Brak"},{"data":"2026.06.13 sobota","od":"8:00","do":"8:45","godziny":"1h00m","group_code":"1","przedmiot":"Modelowanie 3D","typ":"Cw","sala":"S55 15","prowadzacy":"mgr Wojciech Jarosz","zaliczenie":"Zaliczenie ocena","uwagi":"Brak"},{"data":"2026.06.13 sobota","od":"9:00","do":"10:30","godziny":"2h00m","group_code":"2","przedmiot":"Self-branding i zarządzanie marką osobistą","typ":"Cw","sala":"S47 120","prowadzacy":"mgr Oliwia Świątek","zaliczenie":"Zaliczenie ocena","uwagi":"Brak"},{"data":"2026.06.13 sobota","od":"9:00","do":"10:30","godziny":"2h00m","group_code":"1","przedmiot":"Modelowanie 3D","typ":"Cw","sala":"S55 15","prowadzacy":"mgr Wojciech Jarosz","zaliczenie":"Zaliczenie ocena","uwagi":"Brak"},{"data":"2026.06.13 sobota","od":"10:45","do":"12:15","godziny":"2h00m","group_code":"2","przedmiot":"Self-branding i zarządzanie marką osobistą","typ":"Cw","sala":"S47 120","prowadzacy":"mgr Oliwia Świątek","zaliczenie":"Zaliczenie ocena","uwagi":"Brak"},{"data":"2026.06.13 sobota","od":"10:45","do":"12:15","godziny":"2h00m","group_code":"1","przedmiot":"Modelowanie 3D","typ":"Cw","sala":"S55 15","prowadzacy":"mgr Wojciech Jarosz","zaliczenie":"Zaliczenie ocena","uwagi":"Brak"},{"data":"2026.06.13 sobota","od":"12:30","do":"14:00","godziny":"2h00m","group_code":"1","przedmiot":"Modelowanie 3D","typ":"Cw","sala":"S55 15","prowadzacy":"mgr Wojciech Jarosz","zaliczenie":"Zaliczenie ocena","uwagi":"Brak"},{"data":"2026.06.13 sobota","od":"14:15","do":"15:45","godziny":"2h00m","group_code":"1","przedmiot":"Metodologia badań komunikacji społecznej i mediów","typ":"Cw","sala":"S47 10","prowadzacy":"dr Magdalena Parus-Jankowska","zaliczenie":"Zaliczenie ocena","uwagi":"Brak"},{"data":"2026.06.13 sobota","od":"16:00","do":"17:30","godziny":"2h00m","group_code":"1","przedmiot":"Metodologia badań komunikacji społecznej i mediów","typ":"Cw","sala":"S47 10","prowadzacy":"dr Magdalena Parus-Jankowska","zaliczenie":"Zaliczenie ocena","uwagi":"Brak"},{"data":"2026.06.13 sobota","od":"17:45","do":"19:15","godziny":"2h00m","group_code":"1","przedmiot":"Koncepcje zarządzania","typ":"Cw","sala":"S47 120","prowadzacy":"dr inż. Joanna Nowicka","zaliczenie":"Zaliczenie ocena","uwagi":"Brak"},{"data":"2026.06.14 niedziela","od":"8:00","do":"8:45","godziny":"1h00m","group_code":"2","przedmiot":"Modelowanie 3D","typ":"Cw","sala":"S55 308","prowadzacy":"mgr Kacper Korzybski","zaliczenie":"Zaliczenie ocena","uwagi":"Brak"},{"data":"2026.06.14 niedziela","od":"9:00","do":"10:30","godziny":"2h00m","group_code":"1","przedmiot":"Self-branding i zarządzanie marką osobistą","typ":"Cw","sala":"","prowadzacy":"mgr Oliwia Świątek","zaliczenie":"Zaliczenie ocena","uwagi":"Brak"},{"data":"2026.06.14 niedziela","od":"9:00","do":"10:30","godziny":"2h00m","group_code":"2","przedmiot":"Modelowanie 3D","typ":"Cw","sala":"S55 308","prowadzacy":"mgr Kacper Korzybski","zaliczenie":"Zaliczenie ocena","uwagi":"Brak"},{"data":"2026.06.14 niedziela","od":"10:45","do":"12:15","godziny":"2h00m","group_code":"2","przedmiot":"Modelowanie 3D","typ":"Cw","sala":"S55 308","prowadzacy":"mgr Kacper Korzybski","zaliczenie":"Zaliczenie ocena","uwagi":"Brak"},{"data":"2026.06.14 niedziela","od":"10:45","do":"12:15","godziny":"2h00m","group_code":"1","przedmiot":"Self-branding i zarządzanie marką osobistą","typ":"Cw","sala":"","prowadzacy":"mgr Oliwia Świątek","zaliczenie":"Zaliczenie ocena","uwagi":"Brak"},{"data":"2026.06.14 niedziela","od":"12:30","do":"14:00","godziny":"2h00m","group_code":"2","przedmiot":"Modelowanie 3D","typ":"Cw","sala":"S55 308","prowadzacy":"mgr Kacper Korzybski","zaliczenie":"Zaliczenie ocena","uwagi":"Brak"},{"data":"2026.06.14 niedziela","od":"14:15","do":"15:45","godziny":"2h00m","group_code":"2","przedmiot":"Koncepcje zarządzania","typ":"Cw","sala":"S47 312 - prac. matematyczna","prowadzacy":"dr inż. Joanna Nowicka","zaliczenie":"Zaliczenie ocena","uwagi":"Brak"},{"data":"2026.06.14 niedziela","od":"16:00","do":"17:30","godziny":"2h00m","group_code":"2","przedmiot":"Koncepcje zarządzania","typ":"Cw","sala":"S47 312 - prac. matematyczna","prowadzacy":"dr inż. Joanna Nowicka","zaliczenie":"Zaliczenie ocena","uwagi":"Brak"},{"data":"2026.06.27 sobota","od":"8:00","do":"10:30","godziny":"3h00m","group_code":"1","przedmiot":"Sculpting 3D","typ":"Cw","sala":"S55 15","prowadzacy":"mgr Tomasz Wojciechowski","zaliczenie":"Zaliczenie ocena","uwagi":"Brak"},{"data":"2026.06.27 sobota","od":"8:00","do":"10:30","godziny":"3h00m","group_code":"2","przedmiot":"Motion design","typ":"Cw","sala":"S47 216","prowadzacy":"mgr Adrianna Kaim","zaliczenie":"Zaliczenie ocena","uwagi":"Brak"},{"data":"2026.06.27 sobota","od":"10:45","do":"12:15","godziny":"2h00m","group_code":"","przedmiot":"Metodologia badań komunikacji społecznej i mediów","typ":"Wyk","sala":"S55 27-AULA","prowadzacy":"dr Magdalena Parus-Jankowska","zaliczenie":"Zaliczenie ocena","uwagi":"Brak"},{"data":"2026.06.27 sobota","od":"12:30","do":"14:00","godziny":"2h00m","group_code":"","przedmiot":"Metodologia badań komunikacji społecznej i mediów","typ":"Wyk","sala":"S55 27-AULA","prowadzacy":"dr Magdalena Parus-Jankowska","zaliczenie":"Zaliczenie ocena","uwagi":"Brak"},{"data":"2026.06.27 sobota","od":"14:15","do":"15:45","godziny":"2h00m","group_code":"","przedmiot":"Teoria nowych mediów","typ":"Wyk","sala":"S55 27-AULA","prowadzacy":"dr Ewa Kędzia","zaliczenie":"Egzamin","uwagi":"Brak"},{"data":"2026.06.27 sobota","od":"15:55","do":"17:25","godziny":"2h00m","group_code":"","przedmiot":"Teoria nowych mediów","typ":"Wyk","sala":"S55 27-AULA","prowadzacy":"dr Ewa Kędzia","zaliczenie":"Egzamin","uwagi":"Brak"},{"data":"2026.06.27 sobota","od":"17:30","do":"18:15","godziny":"1h00m","group_code":"","przedmiot":"Teoria nowych mediów","typ":"Wyk","sala":"S55 27-AULA","prowadzacy":"dr Ewa Kędzia","zaliczenie":"Egzamin","uwagi":"Brak"},{"data":"2026.06.28 niedziela","od":"8:00","do":"8:45","godziny":"1h00m","group_code":"2","przedmiot":"Modelowanie 3D","typ":"Cw","sala":"S55 15","prowadzacy":"mgr Kacper Korzybski","zaliczenie":"Zaliczenie ocena","uwagi":"Brak"},{"data":"2026.06.28 niedziela","od":"9:00","do":"10:30","godziny":"2h00m","group_code":"2","przedmiot":"Modelowanie 3D","typ":"Cw","sala":"S55 15","prowadzacy":"mgr Kacper Korzybski","zaliczenie":"Zaliczenie ocena","uwagi":"Brak"},{"data":"2026.06.28 niedziela","od":"9:00","do":"10:30","godziny":"2h00m","group_code":"1","przedmiot":"Self-branding i zarządzanie marką osobistą","typ":"Cw","sala":"S47 120","prowadzacy":"mgr Oliwia Świątek","zaliczenie":"Zaliczenie ocena","uwagi":"Brak"},{"data":"2026.06.28 niedziela","od":"10:45","do":"12:15","godziny":"2h00m","group_code":"2","przedmiot":"Modelowanie 3D","typ":"Cw","sala":"S55 15","prowadzacy":"mgr Kacper Korzybski","zaliczenie":"Zaliczenie ocena","uwagi":"Brak"},{"data":"2026.06.28 niedziela","od":"10:45","do":"12:15","godziny":"2h00m","group_code":"1","przedmiot":"Self-branding i zarządzanie marką osobistą","typ":"Cw","sala":"S47 120","prowadzacy":"mgr Oliwia Świątek","zaliczenie":"Zaliczenie ocena","uwagi":"Brak"},{"data":"2026.06.28 niedziela","od":"12:30","do":"14:00","godziny":"2h00m","group_code":"1","przedmiot":"Koncepcje zarządzania","typ":"Cw","sala":"S47 120","prowadzacy":"dr inż. Joanna Nowicka","zaliczenie":"Zaliczenie ocena","uwagi":"Brak"},{"data":"2026.06.28 niedziela","od":"15:00","do":"15:45","godziny":"1h00m","group_code":"","przedmiot":"Koncepcje zarządzania","typ":"Wyk","sala":"S55 27-AULA","prowadzacy":"dr inż. Joanna Nowicka","zaliczenie":"Egzamin","uwagi":"Brak"}]}
